molalkit/__init__.py
molalkit/args.py
molalkit/logging.py
molalkit/utils.py
molalkit/al/__init__.py
molalkit/al/forgetter.py
molalkit/al/learner.py
molalkit/al/run.py
molalkit/al/selection_method.py
molalkit/data/__init__.py
molalkit/data/data.py
molalkit/data/utils.py
molalkit/data/datasets/CYP1A2_Veith.csv
molalkit/data/datasets/CYP2C19_Veith.csv
molalkit/data/datasets/CYP2C9_Substrate_CarbonMangels.csv
molalkit/data/datasets/CYP2C9_Veith.csv
molalkit/data/datasets/CYP2D6_Substrate_CarbonMangels.csv
molalkit/data/datasets/CYP2D6_Veith.csv
molalkit/data/datasets/CYP3A4_Substrate_CarbonMangels.csv
molalkit/data/datasets/CYP3A4_Veith.csv
molalkit/data/datasets/Clearance_Hepatocyte_AZ.csv
molalkit/data/datasets/Half_Life_Obach.csv
molalkit/data/datasets/MDRR1-MDCK_efflux_ratio.csv
molalkit/data/datasets/__init__.py
molalkit/data/datasets/ames.csv
molalkit/data/datasets/aqueous_solubility.csv
molalkit/data/datasets/bace.csv
molalkit/data/datasets/bbb_martins.csv
molalkit/data/datasets/bbbp.csv
molalkit/data/datasets/bioavailability_ma.csv
molalkit/data/datasets/caco2_wang.csv
molalkit/data/datasets/carcinogens_lagunin.csv
molalkit/data/datasets/clintox.csv
molalkit/data/datasets/delaney.csv
molalkit/data/datasets/dili.csv
molalkit/data/datasets/freesolv.csv
molalkit/data/datasets/herg.csv
molalkit/data/datasets/hia_hou.csv
molalkit/data/datasets/hiv.csv
molalkit/data/datasets/human_liver_microsome_stability.csv
molalkit/data/datasets/human_plasma_protein_binding.csv
molalkit/data/datasets/ld50_zhu.csv
molalkit/data/datasets/lipo.csv
molalkit/data/datasets/pdbbind_full.csv
molalkit/data/datasets/pdbbind_refined.csv
molalkit/data/datasets/pgp_broccatelli.csv
molalkit/data/datasets/ppbr_az.csv
molalkit/data/datasets/rat_liver_microsome_stability.csv
molalkit/data/datasets/rat_plasma_protein_binding.csv
molalkit/data/datasets/skin.csv
molalkit/data/datasets/solubility_aqsoldb.csv
molalkit/data/datasets/test_regression.csv
molalkit/data/datasets/vdss_lombardo.csv
molalkit-0.10.1.dist-info/LICENSE
molalkit-0.10.1.dist-info/METADATA
molalkit-0.10.1.dist-info/WHEEL
molalkit-0.10.1.dist-info/entry_points.txt
molalkit-0.10.1.dist-info/top_level.txt
molalkit-0.10.1.dist-info/RECORD
