Metadata-Version: 2.1
Name: molalkit
Version: 0.10.1
Summary: MolALKit: A Toolkit for Active Learning in Molecular Data.
Home-page: https://github.com/RekerLab/MolALKit
Author: Yan Xiang
Author-email: yan.xiang@duke.edu
Classifier: Programming Language :: Python
Classifier: License :: OSI Approved :: MIT License
Classifier: Operating System :: OS Independent
Requires-Python: >=3.8
License-File: LICENSE
Requires-Dist: typed-argument-parser
Requires-Dist: rdkit
Requires-Dist: mgktools
